contentful-2.5.0.dist-info/METADATA
contentful-2.5.0.dist-info/WHEEL
contentful-2.5.0.dist-info/entry_points.txt
contentful-2.5.0.dist-info/licenses/LICENSE
contentful/__init__.py
contentful/array.py
contentful/asset.py
contentful/asset_key.py
contentful/client.py
contentful/content_type.py
contentful/content_type_cache.py
contentful/content_type_field.py
contentful/content_type_field_types.py
contentful/deleted_asset.py
contentful/deleted_entry.py
contentful/entry.py
contentful/errors.py
contentful/locale.py
contentful/resource.py
contentful/resource_builder.py
contentful/space.py
contentful/sync_page.py
contentful/taxonomy_concept.py
contentful/taxonomy_concept_scheme.py
contentful/utils.py
contentful-2.5.0.dist-info/RECORD
