Metadata-Version: 2.1
Name: contentful
Version: 2.5.0
Summary: Contentful Delivery API Client
Keywords: contentful,cms,content
Author-Email: Contentful GmbH <python@contentful.com>
License: MIT
Classifier: Development Status :: 5 - Production/Stable
Classifier: Intended Audience :: Developers
Classifier: License :: OSI Approved :: MIT License
Classifier: Operating System :: OS Independent
Classifier: Programming Language :: Python :: 3
Classifier: Programming Language :: Python :: 3.9
Classifier: Programming Language :: Python :: 3.10
Classifier: Programming Language :: Python :: 3.11
Classifier: Programming Language :: Python :: 3.12
Classifier: Programming Language :: Python :: 3.13
Classifier: Topic :: Software Development :: Libraries :: Python Modules
Project-URL: Homepage, https://github.com/contentful/contentful.py
Project-URL: Documentation, https://contentful.github.io/contentful.py
Project-URL: Repository, https://github.com/contentful/contentful.py
Project-URL: Issues, https://github.com/contentful/contentful.py/issues
Requires-Python: >=3.9
Requires-Dist: requests<3.0,>=2.31.0
Requires-Dist: python-dateutil>=2.8.2
